{
  "n_pairs": 352,
  "n_layers": 36,
  "pairs_by_benchmark": {
    "aime": 8,
    "gsm8k": 188,
    "mmlu": 156
  },
  "safe_layers": [],
  "layer_rankings": [
    {
      "layer": 35,
      "score": 5679.987360777141,
      "norm": 627.0807495117188,
      "consistency": 19.070656291576594,
      "overlap": 0.5250386595726013,
      "safe": false
    },
    {
      "layer": 34,
      "score": 4587.420464056404,
      "norm": 553.0169677734375,
      "consistency": 17.286383835813282,
      "overlap": 0.5201274156570435,
      "safe": false
    },
    {
      "layer": 33,
      "score": 4101.9511508456535,
      "norm": 494.8573303222656,
      "consistency": 17.18149492179222,
      "overlap": 0.5175530910491943,
      "safe": false
    },
    {
      "layer": 32,
      "score": 3520.0866507479195,
      "norm": 463.72137451171875,
      "consistency": 16.37903085219564,
      "overlap": 0.5365445017814636,
      "safe": false
    },
    {
      "layer": 31,
      "score": 3090.2266839745535,
      "norm": 430.0906982421875,
      "consistency": 16.072422313831066,
      "overlap": 0.5529573559761047,
      "safe": false
    },
    {
      "layer": 30,
      "score": 2961.704993935916,
      "norm": 384.1376037597656,
      "consistency": 16.174692927060427,
      "overlap": 0.5233287811279297,
      "safe": false
    },
    {
      "layer": 29,
      "score": 2350.6944414461095,
      "norm": 329.084228515625,
      "consistency": 16.100538117301586,
      "overlap": 0.5563415884971619,
      "safe": false
    },
    {
      "layer": 28,
      "score": 2281.752921573486,
      "norm": 297.63812255859375,
      "consistency": 16.94828283337658,
      "overlap": 0.5476710796356201,
      "safe": false
    },
    {
      "layer": 27,
      "score": 2034.8762302082082,
      "norm": 250.8828125,
      "consistency": 17.811225290306027,
      "overlap": 0.54462069272995,
      "safe": false
    },
    {
      "layer": 26,
      "score": 1821.2841935420965,
      "norm": 216.71109008789062,
      "consistency": 17.617526737816544,
      "overlap": 0.5229634642601013,
      "safe": false
    },
    {
      "layer": 25,
      "score": 1376.231470369053,
      "norm": 182.5002899169922,
      "consistency": 16.04929111062709,
      "overlap": 0.5301361083984375,
      "safe": false
    },
    {
      "layer": 24,
      "score": 1214.2064239316062,
      "norm": 154.12216186523438,
      "consistency": 15.569323577418023,
      "overlap": 0.4939916431903839,
      "safe": false
    },
    {
      "layer": 23,
      "score": 775.9017719285669,
      "norm": 112.03695678710938,
      "consistency": 14.670552177826966,
      "overlap": 0.5279380679130554,
      "safe": false
    },
    {
      "layer": 22,
      "score": 561.8138036852934,
      "norm": 85.1417465209961,
      "consistency": 13.518738613719139,
      "overlap": 0.5118945240974426,
      "safe": false
    },
    {
      "layer": 21,
      "score": 339.6819925633313,
      "norm": 69.15703582763672,
      "consistency": 10.996667153649444,
      "overlap": 0.5533420443534851,
      "safe": false
    },
    {
      "layer": 20,
      "score": 216.93593781858527,
      "norm": 53.411041259765625,
      "consistency": 9.229999194633097,
      "overlap": 0.5599532723426819,
      "safe": false
    },
    {
      "layer": 19,
      "score": 164.68060530305232,
      "norm": 46.56453323364258,
      "consistency": 8.395899124601957,
      "overlap": 0.578769326210022,
      "safe": false
    },
    {
      "layer": 18,
      "score": 109.50580704848083,
      "norm": 36.48845291137695,
      "consistency": 7.908780390551409,
      "overlap": 0.6205345988273621,
      "safe": false
    },
    {
      "layer": 12,
      "score": 50.461201010455504,
      "norm": 13.102395057678223,
      "consistency": 11.788516138762509,
      "overlap": 0.6733010411262512,
      "safe": false
    },
    {
      "layer": 13,
      "score": 48.4533015084327,
      "norm": 14.235919952392578,
      "consistency": 10.244898883411256,
      "overlap": 0.6677766442298889,
      "safe": false
    },
    {
      "layer": 11,
      "score": 48.344416313882505,
      "norm": 11.586649894714355,
      "consistency": 10.485781093662247,
      "overlap": 0.6020874381065369,
      "safe": false
    },
    {
      "layer": 17,
      "score": 44.990227449892345,
      "norm": 26.508316040039062,
      "consistency": 6.07227132386715,
      "overlap": 0.7204980254173279,
      "safe": false
    },
    {
      "layer": 10,
      "score": 39.86926614574538,
      "norm": 11.159232139587402,
      "consistency": 9.04508027543485,
      "overlap": 0.6050050854682922,
      "safe": false
    },
    {
      "layer": 14,
      "score": 36.577044106937166,
      "norm": 15.4984130859375,
      "consistency": 7.33509621737632,
      "overlap": 0.6782522201538086,
      "safe": false
    },
    {
      "layer": 16,
      "score": 35.04373098037206,
      "norm": 22.364696502685547,
      "consistency": 6.544047957516364,
      "overlap": 0.7605577111244202,
      "safe": false
    },
    {
      "layer": 15,
      "score": 32.15779812007789,
      "norm": 16.813203811645508,
      "consistency": 7.065102088639386,
      "overlap": 0.7292818427085876,
      "safe": false
    },
    {
      "layer": 9,
      "score": 20.005429951663444,
      "norm": 9.7518949508667,
      "consistency": 6.476656236279381,
      "overlap": 0.6832562685012817,
      "safe": false
    },
    {
      "layer": 8,
      "score": 18.9866604296546,
      "norm": 7.8692522048950195,
      "consistency": 7.29587703387669,
      "overlap": 0.6692973971366882,
      "safe": false
    },
    {
      "layer": 7,
      "score": 12.615044985493679,
      "norm": 6.354077339172363,
      "consistency": 6.411700721020004,
      "overlap": 0.6903557181358337,
      "safe": false
    },
    {
      "layer": 6,
      "score": 7.743309421827285,
      "norm": 4.729706764221191,
      "consistency": 6.026774605678227,
      "overlap": 0.7283514142036438,
      "safe": false
    },
    {
      "layer": 5,
      "score": 5.356666904559318,
      "norm": 4.304601192474365,
      "consistency": 5.32035564314807,
      "overlap": 0.7661049365997314,
      "safe": false
    },
    {
      "layer": 4,
      "score": 4.652342133894268,
      "norm": 3.387495756149292,
      "consistency": 5.521634086779161,
      "overlap": 0.751271665096283,
      "safe": false
    },
    {
      "layer": 3,
      "score": 4.131550123501129,
      "norm": 2.63378643989563,
      "consistency": 5.950152010706566,
      "overlap": 0.7363641858100891,
      "safe": false
    },
    {
      "layer": 2,
      "score": 2.673001890708191,
      "norm": 1.6832869052886963,
      "consistency": 5.666065946317061,
      "overlap": 0.7197410464286804,
      "safe": false
    },
    {
      "layer": 1,
      "score": 0.9833116968851582,
      "norm": 1.31216561794281,
      "consistency": 5.472324494567955,
      "overlap": 0.8630598783493042,
      "safe": false
    },
    {
      "layer": 0,
      "score": 0.08406927555473725,
      "norm": 0.8910507559776306,
      "consistency": 3.722861016111927,
      "overlap": 0.9746569991111755,
      "safe": false
    }
  ]
}